mcpsock/__init__.py
mcpsock/client.py
mcpsock/server.py
mcpsock-0.1.5.dist-info/licenses/LICENSE
mcpsock-0.1.5.dist-info/METADATA
mcpsock-0.1.5.dist-info/WHEEL
mcpsock-0.1.5.dist-info/top_level.txt
mcpsock-0.1.5.dist-info/RECORD
