Metadata-Version: 2.4
Name: mcpsock
Version: 0.1.5
Summary: WebSocket client and server implementation for FastMCP framework
Author-email: Andy Miller <andythedishwasher@gmail.com>
License-Expression: Apache-2.0
Project-URL: Homepage, https://github.com/thecodekitchen/mcpsock
Project-URL: Bug Tracker, https://github.com/thecodekitchen/mcpsock/issues
Project-URL: Documentation, https://github.com/thecodekitchen/mcpsock#readme
Keywords: websocket,fastmcp,client,server,api
Classifier: Development Status :: 3 - Alpha
Classifier: Intended Audience :: Developers
Classifier: Programming Language :: Python :: 3
Classifier: Programming Language :: Python :: 3.8
Classifier: Programming Language :: Python :: 3.9
Classifier: Programming Language :: Python :: 3.10
Classifier: Programming Language :: Python :: 3.11
Classifier: Programming Language :: Python :: 3.12
Requires-Python: >=3.10
License-File: LICENSE
Requires-Dist: annotated-types>=0.7.0
Requires-Dist: anyio>=4.9.0
Requires-Dist: certifi>=2025.1.31
Requires-Dist: click>=8.1.8
Requires-Dist: coverage>=7.8.0
Requires-Dist: exceptiongroup>=1.2.2
Requires-Dist: fastapi>=0.115.12
Requires-Dist: fastmcp>=2.2.3
Requires-Dist: h11>=0.16.0
Requires-Dist: httpcore>=1.0.9
Requires-Dist: httpx>=0.28.1
Requires-Dist: httpx-sse>=0.4.0
Requires-Dist: idna>=3.10
Requires-Dist: iniconfig>=2.1.0
Requires-Dist: markdown-it-py>=3.0.0
Requires-Dist: mcp>=1.6.0
Requires-Dist: mdurl>=0.1.2
Requires-Dist: openapi-pydantic>=0.5.1
Requires-Dist: packaging>=25.0
Requires-Dist: pluggy>=1.5.0
Requires-Dist: pydantic>=2.11.3
Requires-Dist: pydantic-core>=2.33.1
Requires-Dist: pydantic-settings>=2.9.1
Requires-Dist: pygments>=2.19.1
Requires-Dist: pytest>=8.3.5
Requires-Dist: pytest-asyncio>=0.26.0
Requires-Dist: pytest-cov>=6.1.1
Requires-Dist: python-dotenv>=1.1.0
Requires-Dist: rich>=14.0.0
Requires-Dist: shellingham>=1.5.4
Requires-Dist: sniffio>=1.3.1
Requires-Dist: sse-starlette>=2.3.3
Requires-Dist: starlette>=0.46.2
Requires-Dist: typer>=0.15.2
Requires-Dist: typing-extensions>=4.13.2
Requires-Dist: typing-inspection>=0.4.0
Requires-Dist: uvicorn>=0.34.2
Requires-Dist: websockets>=15.0.1
Provides-Extra: dev
Requires-Dist: pytest>=7.0.0; extra == "dev"
Requires-Dist: pytest-asyncio>=0.18.0; extra == "dev"
Requires-Dist: black>=22.0.0; extra == "dev"
Requires-Dist: isort>=5.10.0; extra == "dev"
Requires-Dist: mypy>=0.950; extra == "dev"
Requires-Dist: flake8>=4.0.0; extra == "dev"
Provides-Extra: test
Requires-Dist: pytest>=7.0.0; extra == "test"
Requires-Dist: pytest-asyncio>=0.18.0; extra == "test"
Requires-Dist: pytest-cov>=3.0.0; extra == "test"
Dynamic: license-file
